shell_genie/__init__.py
shell_genie/backends.py
shell_genie/main.py
shell_genie/utils.py
shell_genie-0.2.10.dist-info/LICENSE
shell_genie-0.2.10.dist-info/WHEEL
shell_genie-0.2.10.dist-info/entry_points.txt
shell_genie-0.2.10.dist-info/METADATA
shell_genie-0.2.10.dist-info/RECORD
